README.rst
setup.py
python_shka_gadgets_openstackclient/__init__.py
python_shka_gadgets_openstackclient/client.py
python_shka_gadgets_openstackclient.egg-info/PKG-INFO
python_shka_gadgets_openstackclient.egg-info/SOURCES.txt
python_shka_gadgets_openstackclient.egg-info/dependency_links.txt
python_shka_gadgets_openstackclient.egg-info/entry_points.txt
python_shka_gadgets_openstackclient.egg-info/requires.txt
python_shka_gadgets_openstackclient.egg-info/top_level.txt
python_shka_gadgets_openstackclient/v1/__init__.py
python_shka_gadgets_openstackclient/v1/vanilla.py