Metadata-Version: 1.2
Name: python-shka-gadgets-openstackclient
Version: 0.5.3
Summary: UNKNOWN
Home-page: https://github.com/shka/python-shka-gadgets-openstackclient
Author: Shintaro Katayama
Author-email: shintaro.katayama@gmail.com
Maintainer: Shintaro Katayama
Maintainer-email: shintaro.katayama@gmail.com
License: UNKNOWN
Platform: UNKNOWN
Classifier: Environment :: OpenStack
Classifier: Programming Language :: Python :: 3
Classifier: License :: OSI Approved :: Apache Software License
